common_datasets/__init__.py
common_datasets/_io.py
common_datasets/_version.py
common_datasets/binary_classification/__init__.py
common_datasets/binary_classification/_binary_classification.py
common_datasets/binary_classification/_binary_classification_part0.py
common_datasets/binary_classification/_binary_classification_part1.py
common_datasets/clustering/__init__.py
common_datasets/clustering/_clustering.py
common_datasets/data/summary_binary_classification.json
common_datasets/data/summary_multiclass_classification.json
common_datasets/data/summary_regression.json
common_datasets/data/classification/abalone/abalone.data.txt
common_datasets/data/classification/abalone/abalone.names.txt
common_datasets/data/classification/abalone-17_vs_7-8-9-10/abalone-17_vs_7-8-9-10-names.txt
common_datasets/data/classification/abalone-17_vs_7-8-9-10/abalone-17_vs_7-8-9-10.dat
common_datasets/data/classification/abalone-17_vs_7-8-9-10/abalone-17_vs_7-8-9-10.dat.bak
common_datasets/data/classification/abalone-17_vs_7-8-9-10/test.dat
common_datasets/data/classification/abalone-17_vs_7-8-9-10/test.dat.bak
common_datasets/data/classification/abalone-19_vs_10-11-12-13/abalone-19_vs_10-11-12-13-names.txt
common_datasets/data/classification/abalone-19_vs_10-11-12-13/abalone-19_vs_10-11-12-13.dat
common_datasets/data/classification/abalone-19_vs_10-11-12-13/abalone-19_vs_10-11-12-13.dat.bak
common_datasets/data/classification/abalone-20_vs_8-9-10/abalone-20_vs_8-9-10-names.txt
common_datasets/data/classification/abalone-20_vs_8-9-10/abalone-20_vs_8-9-10.dat
common_datasets/data/classification/abalone-20_vs_8-9-10/abalone-20_vs_8-9-10.dat.bak
common_datasets/data/classification/abalone-21_vs_8/abalone-21_vs_8-names.txt
common_datasets/data/classification/abalone-21_vs_8/abalone-21_vs_8.dat
common_datasets/data/classification/abalone-21_vs_8/abalone-21_vs_8.dat.bak
common_datasets/data/classification/abalone-3_vs_11/abalone-3_vs_11-names.txt
common_datasets-0.3.10.dist-info/METADATA
common_datasets-0.3.10.dist-info/WHEEL
common_datasets-0.3.10.dist-info/top_level.txt
common_datasets-0.3.10.dist-info/RECORD
