Metadata-Version: 2.1
Name: common-datasets
Version: 0.3.10
Summary: common_datasets
Home-page: http://github.com/gykovacs/common_datasets
Author: Gyorgy Kovacs
Author-email: gyuriofkovacs@gmail.com
Classifier: Development Status :: 3 - Alpha
Classifier: License :: OSI Approved :: MIT License
Classifier: Programming Language :: Python
Classifier: Topic :: Scientific/Engineering :: Artificial Intelligence
Requires-Dist: numpy
Requires-Dist: pandas
Requires-Dist: scipy
Requires-Dist: scikit-learn
Requires-Dist: openpyxl
